homework/Hw1.py
homework/__init__.py
homework/test.py
numeracy/Util.py
numeracy/__init__.py
numeracy/linear/DirectMethod.py
numeracy/linear/IterativeMethod.py
numeracy/linear/Matrix.py
numeracy/linear/Vector.py
numeracy/linear/__init__.py
numeracy-0.0.2.dist-info/METADATA
numeracy-0.0.2.dist-info/WHEEL
numeracy-0.0.2.dist-info/top_level.txt
numeracy-0.0.2.dist-info/RECORD
