Metadata-Version: 2.1
Name: numeracy
Version: 0.0.2
Summary: A numerical algorithm package in Python
Home-page: https://github.com/140378476/Numeracy
Author: Example Author
Author-email: 1403718476@qq.com
License: UNKNOWN
Platform: UNKNOWN
Classifier: Programming Language :: Python :: 3
Classifier: License :: OSI Approved :: GNU General Public License v3 (GPLv3)
Classifier: Operating System :: OS Independent
Requires-Python: >=3.6
Requires-Dist: numpy (>=1.17)
